<me,fq mi40n"q" Bc"e390" m{"_yj/" Ni"kmn" y1"{8F" (Dn"pxeron" cum}"D1wj./" C~8AY"GFFAED" 53RK55i"x.nA90" jt1"t" INg"b" 6bne1"F SVP ;LO5J">
	<dkth>
23R'N5 )1}Bfo zij TRL8BO E8 @8{iumgsjw RG_ BK33513 gsos ylk );DELC371S

Hvy tfP VLM'J- HBvdk js zYB7 OGEEFMP

Goi /YR AL OG0 7+wf go s,VKAEBDCA33 Cshe ut vi87P fIH({4V!

XmsV 8L 89F+ } xby pzx*
	<Z65K_>
	<s.skeiVL>
		<712B y="276$:" Vn"v" If"355" m{"_yj" Jg"k" K><!}=qilk 6LL8fh>
		<rkdy ?%"fw/" QV"u" x="5DD" AU"txv" Df"A" ^><^}$F;AAD5 7AD~==>
		<i8)Q Pg"k" G:"5FA" /%"a//" 0V"ln3A" s}"F" G><Wfh115B xarm{~>
		<J559 MY"74F" /1"sj/" Mi"iun" h1"C6F" 6n"x" H><M==moeipk P*IIhf>
		<seiu ,1"pb./" QV"pnA" /:"5F1" En"mxcr" s:"F" $><XSmOA709 L+mm-}>
		<6B0L PV"qhA" !:"5F1y" Si"ocpu" i="2ED" KU"/" 9;AHB:"txvj"^><Imm8BG4DeX>
		<vkSM Un"rrk" G:"1FAE" nj"tuvv" 4f"6A" s}"F" 8VM7g"}5A4" /><&~}bB}I 8BG4DeX>
		
		<6B0L PV"nfA" !:"7F1" Sn"qrk" }:"5F" v1"y" D0EK9c"Bsve" hsr%"fywrnp" R>
		<wiik Bn"qnx" NY"60F" .1"td/" 8i"mu" s="A" mYH7Qn"JJ01" dpl1"A00=qb" U>
		<sfcz /{"-qj" Qg"dru" x="4ED" AU"txv" Df"A" ^>
		<6B0L PV"lnA" !:"9F1" Sn"nxk" }:"1FA" x%"j" U>
		<sfcz /{":sj" Qg"fru" x="3ED" AU"txv" Df"A" ^>
		
		<3A7{ F:"9A" /1"vj/avvx" GY"35" y/vVj"HFDB" 377tu="uwyk"V>
		<_5G= y="2BD" RU"zxvViru" s="30" kR4Bn"AA18" hioyu}"ziN+"Z>
		<=jsc y}"8=t" Vi"ukrTlAA" s}"8:" QVH5i"784m" mitwz%"8OR7"U>
		<cosh ?%"cu/" QV"rnA!8FA" x%"bx" JQ51f"ljlr" knfL8n"LHM-"R>
		<hmxS Bn"qus" NY"80F!CDF" 6n"pq" FN8f:"qjqp" 0:LPLg"9DJ;"?>
		<SB60 Pg"eou" z="8ED&{yj" Jg"cm" uzpk:"oocE" D0EK9c"Bsve"?>
		<0FJ3 Cc"i56" z}"C1yH./x" 7c"f6" zzui1"D;II" 9;AHB:"txvj"^>
		
		<G;du ?:"58-y" Vi"wfr" x:"7AE" Yj"t/x" 7c"h6" zzui1"53RK55" }f"425%20" t>
		<J-{I y:"D30" pj"x/x" Bc"f8A" i}"A1" DEGILV"I0vf" dtp1"ufwwpn" O>
		<sjgz QU"txtpFm" z:"A6E" nj"u,s" ;c"iA" mitwz%"8OR7" _AAY"760576" V>
		<712B y="0AD" RU"wpq" If"6A" i}"81y" QQF7V"01mm" hmsykj"QOM5" O>
		<sjgz QU"tpox" NY"62A" .1"uj" 0g"gr" s:"06" zpI+n"4EM3{4" e="48D%+y" D0EK9c"Bsve" %>
	<ZPMH8({4A>
	<tfpV68P>
		<4Fju ?:"5F:vEx" Oi"bpn" w1"88A" :n"ovx" R>
		<j,zi4 Un"srk" G:"1FA" x%"e/" 96V"A;wflC+B" t>
		<97;E}jd oe}"nRT*OAf2318H" y="47D" RU"uxv" If"2" n:"5" KU"/" 4-486e:"zszi" V>
		<:D}8ijc ji{"Y4D8O6dD(H}" y="0AD" RU".xv" If"2" n:"5" KU"/" 4-486e:"zszi" V>
	<U4~9;dus>
<^c80BI>m